<?xml version="1.0" encoding="utf-8"?>
<Automata name="Untitled">
<Automaton name="PA" type="Plant">
	<Events>
		<Event id="a" label="a"/>
		<Event id="u1" controllable="false"/>
	</Events>
	<States>
		<State id="pa1" initial="true" accepting="true"/>
		<State id="pa2" accepting="true" cost="0"/>
	</States>
	<Transitions>
		<Transition source="pa1" dest="pa2" event="a"/>
		<Transition source="pa2" dest="pa2" event="u1"/>
	</Transitions>
</Automaton>
<Automaton name="PB" type="Plant">
	<Events>
		<Event id="b" label="b"/>
		<Event id="u2" controllable="false"/>
	</Events>
	<States>
		<State id="pb1" initial="true" accepting="true"/>
		<State id="pb2" accepting="true" cost="0"/>
	</States>
	<Transitions>
		<Transition source="pb1" dest="pb2" event="b"/>
		<Transition source="pb2" dest="pb2" event="u2"/>
	</Transitions>
</Automaton>
<Automaton name="S" type="Supervisor">
	<Events>
		<Event id="a" label="a"/>
		<Event id="b" label="b"/>
		<Event id="u1" controllable="false"/>
		<Event id="u2" controllable="false"/>
	</Events>
	<States>
		<State id="s1" initial="true" accepting="true"/>
		<State id="s2" accepting="true"/>
		<State id="s3" accepting="true"/>
	</States>
	<Transitions>
		<Transition source="s1" dest="s2" event="a"/>
		<Transition source="s1" dest="s3" event="b"/>
		<Transition source="s2" dest="s2" event="u1"/>
		<Transition source="s3" dest="s3" event="u2"/>
	</Transitions>
</Automaton>
<Automaton name="PA SelfLooped" type="Plant">
	<Events>
		<Event id="a" label="a"/>
		<Event id="u1" controllable="false"/>
		<Event id="b" label="b"/>
		<Event id="u2" controllable="false"/>
	</Events>
	<States>
		<State id="pa1" initial="true" accepting="true"/>
		<State id="pa2" accepting="true" cost="0"/>
	</States>
	<Transitions>
		<Transition source="pa1" dest="pa2" event="a"/>
		<Transition source="pa2" dest="pa2" event="u1"/>
		<Transition source="pa2" dest="pa2" event="b"/>
		<Transition source="pa2" dest="pa2" event="u2"/>
		<Transition source="pa1" dest="pa1" event="b"/>
		<Transition source="pa1" dest="pa1" event="u2"/>
	</Transitions>
</Automaton>
<Automaton name="PB SelfLooped" type="Plant">
	<Events>
		<Event id="b" label="b"/>
		<Event id="u2" controllable="false"/>
		<Event id="a" label="a"/>
		<Event id="u1" controllable="false"/>
	</Events>
	<States>
		<State id="pb1" initial="true" accepting="true"/>
		<State id="pb2" accepting="true" cost="0"/>
	</States>
	<Transitions>
		<Transition source="pb1" dest="pb2" event="b"/>
		<Transition source="pb2" dest="pb2" event="u2"/>
		<Transition source="pb2" dest="pb2" event="a"/>
		<Transition source="pb2" dest="pb2" event="u1"/>
		<Transition source="pb1" dest="pb1" event="a"/>
		<Transition source="pb1" dest="pb1" event="u1"/>
	</Transitions>
</Automaton>
</Automata>
